{
  "park_name": "Ingenia Holidays Hunter Valley",
  "slug": "ingenia-holidays-hunter-valley",
  "locations": [
    "nsw/hunter-valley"
  ],
  "total_score": 73.0,
  "classification": "Gold",
  "google_rating": 4.2,
  "review_count": 495,
  "website": "",
  "lat": null,
  "lng": null,
  "wifi_available": "yes",
  "pet_friendly": "yes",
  "executive_summary": "PARK: Ingenia Holidays Hunter Valley\nSCORE: 73/100\nDATE SCORED: 2026-05-14\nREVIEWS ANALYSED: 145\n\nWHY THIS SCORE:\nEntertainment (15/20) — Excellent dual pool setup with one heated pool and spa highly praised by families, jumping pillow very popular with kids, playground and play area well-used, Easter activities included pedal karts and inflatable trampoline, poolside games and sausage sizzles for special events, camp kitchen with pizza oven a highlight, safe for kids to ride bikes around the small park, but limited structured entertainment programs.\n\nNature (14/20) — Located in the heart of Hunter Valley wine country with vineyard surroundings, wildlife frequently spotted and enjoyed by guests, beautifully maintained gardens with roses, leafy cabin positions, communal fire pit area popular, forested feel in some areas, but no beach or creek access, limited shade on powered sites, and busy road proximity detracts from natural ambience.\n\nCleanliness (11/15) — Modern villas and many cabins described as spotless and very clean, amenities consistently praised as clean with bath mats provided, pool area kept spotless, but multiple reports of dirty floors in budget cabins requiring immediate cleaning, some cockroach infestations reported, shelves and microwaves found very dirty, dusty blankets, washing machines stained clothing, and inconsistent housekeeping standards across different accommodation types.\n\nValue (11/15) — Competitive pricing for Hunter Valley location praised by many, good value for 2-bedroom cabins noted, complimentary treats (V drinks, chocolates, wine) appreciated, well-equipped kitchens save dining costs, but concerns about price gouging during concert events, expensive for location given limited spots, budget cabins felt outdated for price, $50 cancellation fees seen as excessive, and some guests felt overcharged for what was received.\n\nSite Size (6/10) — Drive-through sites spacious and easy to access for big rigs, artificial grass keeps sites clean, but multiple complaints that sites are very small especially for larger caravans, tight access and manoeuvring required, no safe car parking at some cabin sites forcing long walks with luggage, cramped powered sites with cars blocking access roads, sites 13-15 and P5-P10 particularly problematic near main road, small park overall with only 27 sites.\n\nSentiment (8/10) — Strong repeat visitation with multiple families returning 2-3 times within 12 months, many enthusiastic recommendations and families saying kids loved it, helpful accommodating staff frequently praised, but offset by some very negative experiences with staff rudeness over cabin allocation and pet policies, intimidating checkout surveillance reported, service lapses with towel provision, poor communication about roadworks and noise, and several guests stating they won't return.\n\nLocation (8/10) — Prime Hunter Valley wine region location on doorstep of vineyards, close to Pokolbin and Lovedale wineries, walking distance to Cessnock town centre (1.5km), convenient for Hunter Valley Gardens and cellar doors, accessible to shops and restaurants, café on-site, but sites backing onto Mount View Road suffer severe noise from traffic, trucks, and motorcycles racing at night requiring sleeping pills and earplugs, near school adds daytime traffic, no beach access.\n\nWHY NOT 100:\nCleanliness standards are highly inconsistent with budget cabins frequently reported as having dirty floors requiring immediate guest cleaning, cockroach infestations, dusty blankets, and poorly maintained fixtures, while villas are spotless. Site size is a significant constraint with cramped powered sites, difficult manoeuvring for large rigs, unsafe car parking blocking access roads, and cabins far from parking causing major inconvenience for families with young children and luggage. Road noise from Mount View Road is severe enough that guests on sites 13-15 report needing sleeping pills and earplugs due to constant truck traffic and motorcycle racing throughout the night.\n\nNOTABLE REVIEW PHRASES:\n\"two amazing pools\", \"kids saying they're happy the car broke down\", \"super safe for kids to zoom on their bikes\", \"floor was filthy\", \"infested with German cockroaches\", \"sites are very small\", \"traffic noise woke us at different hours\", \"had to take sleeping pills and wear ear plugs\", \"so much for the kids to do here\", \"spotless self contained\", \"great camp kitchen with pizza oven\", \"will definitely stay here again\"",
  "rationale_top3": "Entertainment (15/20): Excellent dual pool setup with heated pool and spa highly praised by families, jumping pillow very popular with kids, well-used playground and play areas, Easter activities including pedal karts and inflatable trampoline, camp kitchen with pizza oven a highlight, and safe environment for children to ride bikes throughout the small park. Nature (14/20): Located in the heart of Hunter Valley wine country surrounded by vineyards, wildlife frequently spotted, beautifully maintained gardens with roses, leafy cabin positions, and popular communal fire pit area creating a forested feel in some areas. Cleanliness (11/15): Modern villas and many cabins described as spotless and very clean, amenities consistently praised as clean with bath mats provided, and pool area kept spotless, though budget cabins showed inconsistent standards.",
  "rationale_honourable": "Ingenia Holidays Hunter Valley earns Silver for its excellent twin pool facilities including heated option and spa, very family-friendly amenities with jumping pillow and playground, and prime wine country location. Families particularly praised the well-equipped camp kitchen with pizza oven and fire pit, spacious clean cabins, and helpful staff who provide thoughtful touches like complimentary treats and pet amenities. While cleanliness issues in some budget cabins and site size constraints prevented a Gold rating, the park delivers a solid experience for families visiting the Hunter Valley.",
  "water_fun": "Two pools, heated option, spa, great fun",
  "kids_play": "Jumping pillow, playground, pedal karts, activities",
  "pet_detail": "Pet-friendly cabins available with dog beds and bowls provided; some confusion around villa pet policies with unexpected fees reported.",
  "best_for": "Young families seeking a well-equipped, pool-focused holiday park base for exploring Hunter Valley wineries and attractions.",
  "photo_url_cached": "https://maps.googleapis.com/maps/api/place/photo?maxwidth=800&photo_reference=AaVGc3nWgvWHixqTZtgvN--URXGqo0Rh8kGnfhu6E5XnjU6r6gkCAAfCkLAp61uiyO_f75KhOe_xsbvQPcgvtMV8yeAoRwWtmQZm-0EozVOzwULDO2-D80hGxqqLp8ujJWYwZUgUXPkGuD_iOSWN_gCTtIppAXI5VNKxLjd6OISzy7GGnNVCdeyVfMd1F6oXovQuRjzL-tpRSxcK-salCMZXyh6H9e80sxF7OOaTvxVosOcGlv4qhUzZwkXfL8wfH7mXgVwfT1QBGrGOJaTavA9Y0VKkOWGYYCCnPbim-5cqXCBufSICgXBS2Oe32XfeR9nK8r1dpMNXqTiIT40J2kxxK6NDi9wHWmpAmNJr6ShIFNFMXK4ISLqjkjr4uFO40pf7AK7-3Xd6-8CpvhiJdYdEhL_Zg5J9ncAWhw5Diyd-_-rHhLxeH7ehqy9Y4rF_fg&key=AIzaSyD-wXTs4SJ1MoUCXNS-smGcDaQBxukAtKU",
  "nearest_beach_cached": "",
  "nearest_supermarket_cached": {
    "name": "ALDI",
    "km": 1.377374230857217
  },
  "prices": {},
  "deals": "",
  "notes": "",
  "top_scoring_criteria": [
    "Pool",
    "Playground",
    "Pet Friendly",
    "Nature Setting"
  ],
  "photo_url_override": "https://maps.googleapis.com/maps/api/place/photo?maxwidth=800&photo_reference=AaVGc3nWgvWHixqTZtgvN--URXGqo0Rh8kGnfhu6E5XnjU6r6gkCAAfCkLAp61uiyO_f75KhOe_xsbvQPcgvtMV8yeAoRwWtmQZm-0EozVOzwULDO2-D80hGxqqLp8ujJWYwZUgUXPkGuD_iOSWN_gCTtIppAXI5VNKxLjd6OISzy7GGnNVCdeyVfMd1F6oXovQuRjzL-tpRSxcK-salCMZXyh6H9e80sxF7OOaTvxVosOcGlv4qhUzZwkXfL8wfH7mXgVwfT1QBGrGOJaTavA9Y0VKkOWGYYCCnPbim-5cqXCBufSICgXBS2Oe32XfeR9nK8r1dpMNXqTiIT40J2kxxK6NDi9wHWmpAmNJr6ShIFNFMXK4ISLqjkjr4uFO40pf7AK7-3Xd6-8CpvhiJdYdEhL_Zg5J9ncAWhw5Diyd-_-rHhLxeH7ehqy9Y4rF_fg&key=AIzaSyD-wXTs4SJ1MoUCXNS-smGcDaQBxukAtKU",
  "address": ""
}