[
  {
    "title": "NRMA Jindabyne Holiday Park",
    "subTitle": null,
    "description": "Down-to-earth cabins on a lakefront property offering kitchens, plus a campsite & a caravan park.",
    "price": null,
    "categoryName": "RV park",
    "address": "6 Kosciuszko Rd, Jindabyne NSW 2627, Australia",
    "neighborhood": null,
    "street": "6 Kosciuszko Rd",
    "city": "Jindabyne",
    "postalCode": "2627",
    "state": "New South Wales",
    "countryCode": "AU",
    "website": "https://www.nrmaparksandresorts.com.au/jindabyne?utm_source=googlebusiness&utm_medium=organic&utm_campaign=nrma-googlebusiness&utm_content=jindabyne&utm_term=plcid_3207672256541936747",
    "phone": "+61 2 6456 2249",
    "phoneUnformatted": "+61264562249",
    "claimThisBusiness": false,
    "location": {
      "lat": -36.4133322,
      "lng": 148.619712
    },
    "locatedIn": null,
    "floor": null,
    "plusCode": null,
    "menu": null,
    "servicesLink": null,
    "totalScore": 4.3,
    "permanentlyClosed": false,
    "temporarilyClosed": false,
    "placeId": "ChIJSSUKQfLEPGsRBo2JEDY_-jk",
    "categories": [
      "RV park",
      "Campground",
      "Holiday park"
    ],
    "fid": "0x6b3cc4f2410a2549:0x39fa3f3610898d06",
    "cid": "4177721105777790214",
    "reviewsCount": 826,
    "imagesCount": 1800,
    "imageCategories": [],
    "scrapedAt": "2026-05-26T04:12:46.167Z",
    "reserveTableUrl": null,
    "googleFoodUrl": null,
    "hotelStars": "3-star hotel",
    "hotelDescription": "Set on the shore of Lake Jindabyne, these cozy holiday cabins are also 20 km from the scenic Kosciuszko National Park and 30 km from skiing at Smiggin Holes.\n Streamlined studios to 2-bedroom cabins sleep between 4-6 people and come with kitchens, balconies and flat-screen TVs. Some cabins add air-conditioning, lake views and wood-panelling.\n There's an expansive lawn area near the lake, as well as a campsite and a caravan park on the premises.",
    "checkInDate": "2026-06-07",
    "checkOutDate": "2026-06-08",
    "hotelAds": [],
    "popularTimesLiveText": null,
    "popularTimesLivePercent": null,
    "popularTimesHistogram": {},
    "openingHours": [],
    "peopleAlsoSearch": [],
    "placesTags": [],
    "reviewsTags": [],
    "additionalInfo": {
      "Amenities": [
        {
          "Free Wi-Fi": true
        }
      ]
    },
    "gasPrices": [],
    "url": "https://www.google.com/maps/search/?api=1&query=NRMA%20Jindabyne%20Holiday%20Park&query_place_id=ChIJSSUKQfLEPGsRBo2JEDY_-jk",
    "searchPageUrl": "https://www.google.com/maps/search/caravan%20parks%20Snowy%20Mountains%20NSW?hl=en",
    "searchString": "caravan parks Snowy Mountains NSW",
    "language": "en",
    "rank": 1,
    "isAdvertisement": false,
    "imageUrl": "https://lh3.googleusercontent.com/gps-cs-s/APNQkAEUCZOb4jtxvKYsmc4UsTJfdyVX9Rq5JhTFNj2EToTsB1l86RL5mNP_ahj0S7rxh_D5o_Zb2wa1mLxLZBVVqpXspsNVGqoN3R_lDScfBl5u0e7Zci6IDOocf4lVZtU08aj-AWoqFA=w408-h305-k-no",
    "kgmid": "/g/11h19rb8l"
  },
  {
    "title": "Kosciuszko Tourist Park",
    "subTitle": null,
    "description": "Straightforward, rustic chalets & wood cabins, some with BBQs & decks, plus a guest lounge.",
    "price": "$25",
    "categoryName": "RV park",
    "address": "1400 Kosciuszko Rd, Jindabyne NSW 2627, Australia",
    "neighborhood": null,
    "street": "1400 Kosciuszko Rd",
    "city": "Jindabyne",
    "postalCode": "2627",
    "state": "New South Wales",
    "countryCode": "AU",
    "website": "http://www.kosipark.com.au/",
    "phone": "+61 2 6456 2224",
    "phoneUnformatted": "+61264562224",
    "claimThisBusiness": false,
    "location": {
      "lat": -36.3520584,
      "lng": 148.5650634
    },
    "locatedIn": null,
    "floor": null,
    "plusCode": null,
    "menu": null,
    "servicesLink": null,
    "totalScore": 4.3,
    "permanentlyClosed": false,
    "temporarilyClosed": false,
    "placeId": "ChIJAQAAAACxPGsRMnvRUn6Xksg",
    "categories": [
      "RV park",
      "Hotel"
    ],
    "fid": "0x6b3cb10000000001:0xc892977e52d17b32",
    "cid": "14452780722996476722",
    "reviewsCount": 425,
    "imagesCount": 519,
    "imageCategories": [],
    "scrapedAt": "2026-05-26T04:12:46.168Z",
    "reserveTableUrl": null,
    "googleFoodUrl": null,
    "hotelStars": "3-star hotel",
    "hotelDescription": "Surrounded by forest, this collection of simple chalets and cabins in Kosciuszko National Park is 6 km from Creel Bay and 18 km from Perisher ski resort.\n No-nonsense wood cabins have kitchenettes, shared bathrooms and fire pits. The modestly furnished chalets with en suite facilities offer 2 or 3 bedrooms, kitchens and flat-screen TVs; some add bunk beds, BBQ grills and/or decks.\n Amenities include a communal kitchen, and a guest lounge with a log fire. A campground is on-site.",
    "checkInDate": "2026-06-07",
    "checkOutDate": "2026-06-08",
    "hotelAds": [],
    "popularTimesLiveText": null,
    "popularTimesLivePercent": null,
    "popularTimesHistogram": {},
    "openingHours": [],
    "peopleAlsoSearch": [],
    "placesTags": [],
    "reviewsTags": [],
    "additionalInfo": {
      "Crowd": [
        {
          "LGBTQ+ friendly": true
        }
      ]
    },
    "gasPrices": [],
    "url": "https://www.google.com/maps/search/?api=1&query=Kosciuszko%20Tourist%20Park&query_place_id=ChIJAQAAAACxPGsRMnvRUn6Xksg",
    "searchPageUrl": "https://www.google.com/maps/search/caravan%20parks%20Snowy%20Mountains%20NSW?hl=en",
    "searchString": "caravan parks Snowy Mountains NSW",
    "language": "en",
    "rank": 2,
    "isAdvertisement": false,
    "imageUrl": "https://lh3.googleusercontent.com/gps-cs-s/APNQkAHBE19-9W8fvhzlRLoNWrlzIrf7QoH47yitBd6x_0bsnwWnBdsbZhio9vZ8erDf1AsJNjltJNpAaz4OizgSdNuJXmXg2kOoYR6zJtwD48RfXWxOXiePY7P1c-73Fl61YqoQrde1Ag=w408-h244-k-no",
    "kgmid": "/g/1tmg6qq1"
  },
  {
    "title": "Snowy River Holiday Park",
    "subTitle": null,
    "description": null,
    "price": null,
    "categoryName": "RV park",
    "address": "1 Hamilton St, Dalgety NSW 2628, Australia",
    "neighborhood": null,
    "street": "1 Hamilton St",
    "city": "Dalgety",
    "postalCode": "2628",
    "state": "New South Wales",
    "countryCode": "AU",
    "website": "http://www.snowyriverholidaypark.com.au/",
    "phone": "+61 2 6456 5000",
    "phoneUnformatted": "+61264565000",
    "claimThisBusiness": false,
    "location": {
      "lat": -36.5032519,
      "lng": 148.8333218
    },
    "locatedIn": null,
    "floor": null,
    "plusCode": null,
    "menu": null,
    "servicesLink": null,
    "totalScore": 4.7,
    "permanentlyClosed": false,
    "temporarilyClosed": false,
    "placeId": "ChIJJ-5oOMruPGsRpl9pdnx_uLM",
    "categories": [
      "RV park",
      "Campground",
      "Gas shop",
      "General store",
      "Holiday park",
      "Self-catering accommodation"
    ],
    "fid": "0x6b3ceeca3868ee27:0xb3b87f7c76695fa6",
    "cid": "12950240901043150758",
    "reviewsCount": 223,
    "imagesCount": 486,
    "imageCategories": [],
    "scrapedAt": "2026-05-26T04:12:46.168Z",
    "reserveTableUrl": null,
    "googleFoodUrl": null,
    "hotelStars": "RV park",
    "hotelDescription": null,
    "checkInDate": "2026-06-07",
    "checkOutDate": "2026-06-08",
    "hotelAds": [],
    "popularTimesLiveText": null,
    "popularTimesLivePercent": null,
    "popularTimesHistogram": {},
    "openingHours": [],
    "peopleAlsoSearch": [],
    "placesTags": [],
    "reviewsTags": [],
    "additionalInfo": {
      "Crowd": [
        {
          "LGBTQ+ friendly": true
        }
      ],
      "Amenities": [
        {
          "Free Wi-Fi": true
        }
      ]
    },
    "gasPrices": [],
    "url": "https://www.google.com/maps/search/?api=1&query=Snowy%20River%20Holiday%20Park&query_place_id=ChIJJ-5oOMruPGsRpl9pdnx_uLM",
    "searchPageUrl": "https://www.google.com/maps/search/caravan%20parks%20Snowy%20Mountains%20NSW?hl=en",
    "searchString": "caravan parks Snowy Mountains NSW",
    "language": "en",
    "rank": 3,
    "isAdvertisement": false,
    "imageUrl": "https://lh3.googleusercontent.com/gps-cs-s/APNQkAGFXmj5dXO-Z9043WbXggstU6Q5xEDrrEUCqZhEARYA6eInGU1iOOd53IM2iUCRfodRA2YCgPPg9PD9865RHwUedl1H0ZJ4ZRVoWHZ_oMqezgpOSM9NBM5OKoFIOrU2CJnxRYS8iHityJrM=w408-h306-k-no",
    "kgmid": "/g/1tgf7yzv"
  },
  {
    "title": "Discovery Parks - Jindabyne",
    "subTitle": null,
    "description": "Basic bunk rooms & modest cabins at a rural pick offering activities such as fishing and boat hire.",
    "price": null,
    "categoryName": "RV park",
    "address": "6532 Kosciuszko Rd, Jindabyne NSW 2627, Australia",
    "neighborhood": null,
    "street": "6532 Kosciuszko Rd",
    "city": "Jindabyne",
    "postalCode": "2627",
    "state": "New South Wales",
    "countryCode": "AU",
    "website": "https://www.discoveryholidayparks.com.au/caravan-parks/new-south-wales/snowy-mountains/jindabyne?utm_source=google&utm_medium=organic&utm_campaign=gmb&utm_term=visit-website&utm_content=DHP-NSW-Jindabyne",
    "phone": "+61 2 6456 2099",
    "phoneUnformatted": "+61264562099",
    "claimThisBusiness": false,
    "location": {
      "lat": -36.4104003,
      "lng": 148.5965423
    },
    "locatedIn": null,
    "floor": null,
    "plusCode": null,
    "menu": null,
    "servicesLink": null,
    "totalScore": 4.2,
    "permanentlyClosed": false,
    "temporarilyClosed": false,
    "placeId": "ChIJQ4Rs6APFPGsRu2nBjpUPyl0",
    "categories": [
      "RV park",
      "Hotel"
    ],
    "fid": "0x6b3cc503e86c8443:0x5dca0f958ec169bb",
    "cid": "6758231325842434491",
    "reviewsCount": 715,
    "imagesCount": 1099,
    "imageCategories": [],
    "scrapedAt": "2026-05-26T04:12:46.168Z",
    "reserveTableUrl": null,
    "googleFoodUrl": null,
    "hotelStars": "4-star hotel",
    "hotelDescription": "Overlooking Lake Jindabyne, this relaxed holiday park is 4 km from Jindabyne Airport and 6 km from the edge of Kosciuszko National Park.\n Simple dorms come with bunk beds and shared bathrooms. There are also basic open-plan cabins with beds, bunk beds, kitchenettes and flat-screen TVs. Some offer air-conditioning, and upgraded options feature whirlpool tubs.\n Grounds include BBQ facilities, boat ramps and hire, a playground and tennis courts. There's also a game room, a convenience store, a sauna and a communal whirlpool tub. Activities include fishing, mountain biking, white-water rafting, horse riding and winter skiing.",
    "checkInDate": "2026-06-07",
    "checkOutDate": "2026-06-08",
    "hotelAds": [],
    "popularTimesLiveText": null,
    "popularTimesLivePercent": null,
    "popularTimesHistogram": {},
    "openingHours": [],
    "peopleAlsoSearch": [],
    "placesTags": [],
    "reviewsTags": [],
    "additionalInfo": {
      "Service options": [
        {
          "Onsite services": true
        }
      ],
      "Accessibility": [
        {
          "Wheelchair accessible entrance": true
        },
        {
          "Wheelchair accessible parking lot": true
        },
        {
          "Wheelchair accessible restroom": true
        }
      ],
      "Offerings": [
        {
          "RV camping": true
        },
        {
          "RV electric hookup": true
        },
        {
          "RV water hookup": true
        }
      ],
      "Activities": [
        {
          "Hiking": true
        }
      ],
      "Payments": [
        {
          "Camping fee": true
        },
        {
          "Credit cards": true
        },
        {
          "Debit cards": true
        },
        {
          "NFC mobile payments": true
        },
        {
          "Credit cards": true
        }
      ],
      "Children": [
        {
          "Playground": true
        }
      ],
      "Parking": [
        {
          "Free parking lot": true
        }
      ],
      "Pets": [
        {
          "Dogs allowed": true
        }
      ],
      "Amenities": [
        {
          "Free Wi-Fi": true
        }
      ]
    },
    "gasPrices": [],
    "url": "https://www.google.com/maps/search/?api=1&query=Discovery%20Parks%20-%20Jindabyne&query_place_id=ChIJQ4Rs6APFPGsRu2nBjpUPyl0",
    "searchPageUrl": "https://www.google.com/maps/search/caravan%20parks%20Snowy%20Mountains%20NSW?hl=en",
    "searchString": "caravan parks Snowy Mountains NSW",
    "language": "en",
    "rank": 4,
    "isAdvertisement": false,
    "imageUrl": "https://d2hyz2bfif3cr8.cloudfront.net/imageRepo/3/0/180/346/248/21273_jindabyne_standard_cabin_s4_a_S.jpg",
    "kgmid": "/g/1txfp9r_"
  },
  {
    "title": "Cooma Holiday Park",
    "subTitle": null,
    "description": null,
    "price": null,
    "categoryName": "RV park",
    "address": "286 Sharp St, Cooma NSW 2630, Australia",
    "neighborhood": null,
    "street": "286 Sharp St",
    "city": "Cooma",
    "postalCode": "2630",
    "state": "New South Wales",
    "countryCode": "AU",
    "website": "http://www.coomaholidaypark.com.au/",
    "phone": "+61 2 6452 1828",
    "phoneUnformatted": "+61264521828",
    "claimThisBusiness": false,
    "location": {
      "lat": -36.2400083,
      "lng": 149.1104009
    },
    "locatedIn": null,
    "floor": null,
    "plusCode": null,
    "menu": null,
    "servicesLink": null,
    "totalScore": 4,
    "permanentlyClosed": false,
    "temporarilyClosed": false,
    "placeId": "ChIJtcYpECaoPWsRPCK0TVWGUGI",
    "categories": [
      "RV park",
      "Cabin rental agency",
      "Resort hotel"
    ],
    "fid": "0x6b3da8261029c6b5:0x625086554db4223c",
    "cid": "7084309914787783228",
    "reviewsCount": 382,
    "imagesCount": 130,
    "imageCategories": [],
    "scrapedAt": "2026-05-26T04:12:46.169Z",
    "reserveTableUrl": null,
    "googleFoodUrl": null,
    "hotelStars": "3-star hotel",
    "hotelDescription": null,
    "checkInDate": "2026-06-07",
    "checkOutDate": "2026-06-08",
    "hotelAds": [],
    "popularTimesLiveText": null,
    "popularTimesLivePercent": null,
    "popularTimesHistogram": {},
    "openingHours": [],
    "peopleAlsoSearch": [],
    "placesTags": [],
    "reviewsTags": [],
    "additionalInfo": {
      "Service options": [
        {
          "Onsite services": true
        }
      ],
      "Accessibility": [
        {
          "Wheelchair accessible entrance": true
        },
        {
          "Wheelchair accessible parking lot": true
        },
        {
          "Wheelchair accessible restroom": true
        }
      ],
      "Offerings": [
        {
          "RV camping": true
        },
        {
          "RV electric hookup": true
        },
        {
          "RV water hookup": true
        }
      ],
      "Payments": [
        {
          "Camping fee": true
        },
        {
          "Credit cards": true
        },
        {
          "Debit cards": true
        },
        {
          "NFC mobile payments": true
        }
      ],
      "Children": [
        {
          "Playground": true
        }
      ],
      "Pets": [
        {
          "Dogs allowed": true
        }
      ]
    },
    "gasPrices": [],
    "url": "https://www.google.com/maps/search/?api=1&query=Cooma%20Holiday%20Park&query_place_id=ChIJtcYpECaoPWsRPCK0TVWGUGI",
    "searchPageUrl": "https://www.google.com/maps/search/caravan%20parks%20Snowy%20Mountains%20NSW?hl=en",
    "searchString": "caravan parks Snowy Mountains NSW",
    "language": "en",
    "rank": 5,
    "isAdvertisement": false,
    "imageUrl": "https://lh3.googleusercontent.com/gps-cs-s/APNQkAH09oIXQ3tLVCaNPL7cOgXOSnr3-B80rzMnKJXGTRJEJngLgTaXcmviVJqKXszEbXia3KJAKZsr2TRYwOThLNg9Hh7ELsjF8V_j2-D8KKH_FEoun6Bsi9SmOdSjg71yW-UMKpVQj69qlH5E=w408-h473-k-no",
    "kgmid": "/g/1v_z4h94"
  },
  {
    "title": "Thredbo Diggings campground",
    "subTitle": null,
    "description": null,
    "price": null,
    "categoryName": "Campground",
    "address": "Bullocks Walking Track, Bullocks Flat NSW 2627, Australia",
    "neighborhood": null,
    "street": "Bullocks Walking Track",
    "city": "Bullocks Flat",
    "postalCode": "2627",
    "state": "NSW",
    "countryCode": "AU",
    "website": "https://www.nationalparks.nsw.gov.au/camping-and-accommodation/campgrounds/thredbo-diggings-campground?utm_source=google&utm_medium=organic&utm_campaign=Google%20My%20Business%20Page&utm_term=plcid_7746497397052394964&utm_content=Thredbo%20Diggings%20campground%20-%20Kosciuszko%20National%20Park",
    "phone": "+61 2 6450 5600",
    "phoneUnformatted": "+61264505600",
    "claimThisBusiness": false,
    "location": {
      "lat": -36.4470963,
      "lng": 148.425368
    },
    "locatedIn": null,
    "floor": null,
    "plusCode": null,
    "menu": null,
    "servicesLink": null,
    "totalScore": 4.7,
    "permanentlyClosed": false,
    "temporarilyClosed": false,
    "placeId": "ChIJSd5a3FPKPGsRKFQjBXZ_CpE",
    "categories": [
      "Campground"
    ],
    "fid": "0x6b3cca53dc5ade49:0x910a7f7605235428",
    "cid": "10451306030135727144",
    "reviewsCount": 243,
    "imagesCount": 865,
    "imageCategories": [],
    "scrapedAt": "2026-05-26T04:12:46.169Z",
    "reserveTableUrl": null,
    "googleFoodUrl": null,
    "hotelStars": null,
    "hotelDescription": null,
    "checkInDate": null,
    "checkOutDate": null,
    "hotelAds": [],
    "popularTimesLiveText": null,
    "popularTimesLivePercent": null,
    "popularTimesHistogram": {},
    "openingHours": [],
    "peopleAlsoSearch": [],
    "placesTags": [],
    "reviewsTags": [],
    "additionalInfo": {
      "Accessibility": [
        {
          "Wheelchair accessible entrance": true
        },
        {
          "Wheelchair accessible parking lot": true
        }
      ],
      "Amenities": [
        {
          "Public restroom": true
        },
        {
          "Restroom": true
        },
        {
          "Running water": true
        },
        {
          "Tent sites": true
        }
      ],
      "Payments": [
        {
          "Camping fee": true
        }
      ],
      "Parking": [
        {
          "Paid parking garage": true
        },
        {
          "Paid parking lot": true
        }
      ]
    },
    "gasPrices": [],
    "url": "https://www.google.com/maps/search/?api=1&query=Thredbo%20Diggings%20campground&query_place_id=ChIJSd5a3FPKPGsRKFQjBXZ_CpE",
    "searchPageUrl": "https://www.google.com/maps/search/caravan%20parks%20Snowy%20Mountains%20NSW?hl=en",
    "searchString": "caravan parks Snowy Mountains NSW",
    "language": "en",
    "rank": 6,
    "isAdvertisement": false,
    "imageUrl": "https://lh3.googleusercontent.com/gps-cs-s/APNQkAEaugFCDbafwG680BPR2ERxALdAJcqG6R-DbCGC2s_Y534MRawTUCCghCPPM7xNVW9_ZZ3sFVpjx38LCRVXrVe0OcE9nQK2VSb9c-Sdzk0L1yVZlWgKaxQ8dC9b7BXQ0Ln71VSe=w408-h306-k-no",
    "kgmid": "/g/12hm0ys2w"
  },
  {
    "title": "Rainbow Pines Tourist Caravan Park",
    "subTitle": null,
    "description": null,
    "price": null,
    "categoryName": "RV park",
    "address": "Lucas St, Old Adaminaby NSW 2629, Australia",
    "neighborhood": null,
    "street": "Lucas St",
    "city": "Old Adaminaby",
    "postalCode": "2629",
    "state": "New South Wales",
    "countryCode": "AU",
    "website": "http://www.rainbowpines.com.au/",
    "phone": "+61 2 6454 2317",
    "phoneUnformatted": "+61264542317",
    "claimThisBusiness": true,
    "location": {
      "lat": -36.0402908,
      "lng": 148.7063293
    },
    "locatedIn": null,
    "floor": null,
    "plusCode": null,
    "menu": null,
    "servicesLink": null,
    "totalScore": 4.3,
    "permanentlyClosed": false,
    "temporarilyClosed": false,
    "placeId": "ChIJvVhRV7A9PWsRdmE6x84mKWA",
    "categories": [
      "RV park"
    ],
    "fid": "0x6b3d3db0575158bd:0x602926cec73a6176",
    "cid": "6929112171233829238",
    "reviewsCount": 142,
    "imagesCount": 208,
    "imageCategories": [],
    "scrapedAt": "2026-05-26T04:12:46.169Z",
    "reserveTableUrl": null,
    "googleFoodUrl": null,
    "hotelStars": "3-star hotel",
    "hotelDescription": null,
    "checkInDate": "2026-06-07",
    "checkOutDate": "2026-06-08",
    "hotelAds": [],
    "popularTimesLiveText": null,
    "popularTimesLivePercent": null,
    "popularTimesHistogram": {},
    "openingHours": [],
    "peopleAlsoSearch": [],
    "placesTags": [],
    "reviewsTags": [],
    "additionalInfo": {
      "Accessibility": [
        {
          "Wheelchair accessible entrance": true
        },
        {
          "Wheelchair accessible parking lot": true
        },
        {
          "Wheelchair accessible restroom": true
        }
      ],
      "Offerings": [
        {
          "RV camping": true
        },
        {
          "RV electric hookup": true
        }
      ],
      "Payments": [
        {
          "Credit cards": true
        },
        {
          "Debit cards": true
        },
        {
          "NFC mobile payments": true
        },
        {
          "Credit cards": true
        }
      ],
      "Pets": [
        {
          "Dogs allowed": true
        }
      ]
    },
    "gasPrices": [],
    "url": "https://www.google.com/maps/search/?api=1&query=Rainbow%20Pines%20Tourist%20Caravan%20Park&query_place_id=ChIJvVhRV7A9PWsRdmE6x84mKWA",
    "searchPageUrl": "https://www.google.com/maps/search/caravan%20parks%20Snowy%20Mountains%20NSW?hl=en",
    "searchString": "caravan parks Snowy Mountains NSW",
    "language": "en",
    "rank": 7,
    "isAdvertisement": false,
    "imageUrl": "https://images.trvl-media.com/lodging/18000000/17460000/17458700/17458697/ec4941ce_z.jpg",
    "kgmid": "/g/1wl4qs67"
  },
  {
    "title": "Adventist Alpine Village",
    "subTitle": null,
    "description": "Informal lodge set on bushland offering tennis, volleyball & basketball courts, plus BBQs.",
    "price": "$195",
    "categoryName": "Lodging",
    "address": "122 Tinworth Dr, Jindabyne NSW 2627, Australia",
    "neighborhood": null,
    "street": "122 Tinworth Dr",
    "city": "Jindabyne",
    "postalCode": "2627",
    "state": "New South Wales",
    "countryCode": "AU",
    "website": "https://www.alpinevillage.com.au/",
    "phone": "+61 2 6456 2738",
    "phoneUnformatted": "+61264562738",
    "claimThisBusiness": false,
    "location": {
      "lat": -36.4317697,
      "lng": 148.5910116
    },
    "locatedIn": null,
    "floor": null,
    "plusCode": null,
    "menu": null,
    "servicesLink": null,
    "totalScore": 4.7,
    "permanentlyClosed": false,
    "temporarilyClosed": false,
    "placeId": "ChIJdfmJTrbFPGsR9zowRO79JUY",
    "categories": [
      "Lodging"
    ],
    "fid": "0x6b3cc5b64e89f975:0x4625fdee44303af7",
    "cid": "5054725356581305079",
    "reviewsCount": 286,
    "imagesCount": 288,
    "imageCategories": [],
    "scrapedAt": "2026-05-26T04:12:46.169Z",
    "reserveTableUrl": null,
    "googleFoodUrl": null,
    "hotelStars": "Lodging",
    "hotelDescription": "Set on bushland, this laid-back lodge is 2 km from Barry Way Road, 14 km from Lake Jindabyne and 35 km from ski lifts at Perisher Ski Resort.\n Casual rooms offer bunk beds and en suite bathrooms, plus access to a communal kitchen. Upgraded quarters add minifridges, sitting areas and/or kitchenettes. The 1- and 2-bedroom cabins have flat-screen TVs, separate living areas, kitchens and terraces.\n Amenities include tennis, volleyball and basketball courts, plus BBQs and a playground. There's also a coin-operated laundry and a campsite. Minimum-stay rules may apply.",
    "checkInDate": "2026-06-07",
    "checkOutDate": "2026-06-08",
    "hotelAds": [],
    "popularTimesLiveText": null,
    "popularTimesLivePercent": null,
    "popularTimesHistogram": {},
    "openingHours": [],
    "peopleAlsoSearch": [],
    "placesTags": [],
    "reviewsTags": [],
    "additionalInfo": {
      "Service options": [
        {
          "Onsite services": true
        }
      ],
      "Accessibility": [
        {
          "Wheelchair accessible entrance": true
        },
        {
          "Wheelchair accessible parking lot": true
        }
      ],
      "Amenities": [
        {
          "Free Wi-Fi": true
        }
      ]
    },
    "gasPrices": [],
    "url": "https://www.google.com/maps/search/?api=1&query=Adventist%20Alpine%20Village&query_place_id=ChIJdfmJTrbFPGsR9zowRO79JUY",
    "searchPageUrl": "https://www.google.com/maps/search/caravan%20parks%20Snowy%20Mountains%20NSW?hl=en",
    "searchString": "caravan parks Snowy Mountains NSW",
    "language": "en",
    "rank": 8,
    "isAdvertisement": false,
    "imageUrl": "https://lh3.googleusercontent.com/gps-cs-s/APNQkAE8KJUdRTtrQYb0YbhNuQU53vFBetO-7Dh2TQBQOWdE3lR6W_5sWNZ6FnvmQd8vobi1eV3egcb07NCIvMXKUo6p37pdUQxKQcYEaZWBmNZ7BTB_SQ0lIMSK6vTtJ5OYqqsQ0ndm=w775-h240-k-no",
    "kgmid": "/g/1w8wb5fy"
  },
  {
    "title": "Snowy Mountains Retreat",
    "subTitle": null,
    "description": null,
    "price": null,
    "categoryName": "Serviced accommodation",
    "address": "10 Mowamba Way, Jindabyne NSW 2627, Australia",
    "neighborhood": null,
    "street": "10 Mowamba Way",
    "city": "Jindabyne",
    "postalCode": "2627",
    "state": "New South Wales",
    "countryCode": "AU",
    "website": "http://snowymountainsretreat.com/",
    "phone": "",
    "phoneUnformatted": "",
    "claimThisBusiness": false,
    "location": {
      "lat": -36.4680666,
      "lng": 148.6032491
    },
    "locatedIn": null,
    "floor": null,
    "plusCode": null,
    "menu": null,
    "servicesLink": null,
    "totalScore": 5,
    "permanentlyClosed": false,
    "temporarilyClosed": false,
    "placeId": "ChIJWfJHsBzHPGsRy-Ok9Y4rm-U",
    "categories": [
      "Serviced accommodation"
    ],
    "fid": "0x6b3cc71cb047f259:0xe59b2b8ef5a4e3cb",
    "cid": "16544865549082223563",
    "reviewsCount": 5,
    "imagesCount": 66,
    "imageCategories": [],
    "scrapedAt": "2026-05-26T04:12:46.169Z",
    "reserveTableUrl": null,
    "googleFoodUrl": null,
    "hotelStars": "Serviced accommodation",
    "hotelDescription": null,
    "checkInDate": "2026-06-07",
    "checkOutDate": "2026-06-08",
    "hotelAds": [],
    "popularTimesLiveText": null,
    "popularTimesLivePercent": null,
    "popularTimesHistogram": {},
    "openingHours": [],
    "peopleAlsoSearch": [],
    "placesTags": [],
    "reviewsTags": [],
    "additionalInfo": {
      "Amenities": [
        {
          "Free Wi-Fi": true
        },
        {
          "Free breakfast": true
        }
      ]
    },
    "gasPrices": [],
    "url": "https://www.google.com/maps/search/?api=1&query=Snowy%20Mountains%20Retreat&query_place_id=ChIJWfJHsBzHPGsRy-Ok9Y4rm-U",
    "searchPageUrl": "https://www.google.com/maps/search/caravan%20parks%20Snowy%20Mountains%20NSW?hl=en",
    "searchString": "caravan parks Snowy Mountains NSW",
    "language": "en",
    "rank": 9,
    "isAdvertisement": false,
    "imageUrl": "https://lh3.googleusercontent.com/gps-cs-s/APNQkAHOjfMI3VcNRxMpU3EWmd7bKRU92A4COUWSbrdKb2l0lgWqjRFE62KXYE02Rd2-0k4lnB6l9yu3Ps-AeSnNHrGVv_iDpxclMkWcMKdFIXBJ3ItKarnesiTmBtiYXvC7fpSXw38=w408-h306-k-no",
    "kgmid": "/g/11s75d0yq0"
  },
  {
    "title": "The Alpine Tourist Park, Adaminaby",
    "subTitle": null,
    "description": null,
    "price": null,
    "categoryName": "RV park",
    "address": "2 Lett St, Adaminaby NSW 2629, Australia",
    "neighborhood": null,
    "street": "2 Lett St",
    "city": "Adaminaby",
    "postalCode": "2629",
    "state": "New South Wales",
    "countryCode": "AU",
    "website": "http://www.alpinetouristpark.com.au/",
    "phone": "+61 433 303 576",
    "phoneUnformatted": "+61433303576",
    "claimThisBusiness": false,
    "location": {
      "lat": -35.9964523,
      "lng": 148.7698211
    },
    "locatedIn": null,
    "floor": null,
    "plusCode": null,
    "menu": null,
    "servicesLink": null,
    "totalScore": 4.4,
    "permanentlyClosed": false,
    "temporarilyClosed": false,
    "placeId": "ChIJHyYAkKcVPWsRxyRL4nAd6do",
    "categories": [
      "RV park",
      "Camping cabin",
      "Hotel"
    ],
    "fid": "0x6b3d15a79000261f:0xdae91d70e24b24c7",
    "cid": "15774171540511990983",
    "reviewsCount": 148,
    "imagesCount": 84,
    "imageCategories": [],
    "scrapedAt": "2026-05-26T04:12:46.169Z",
    "reserveTableUrl": null,
    "googleFoodUrl": null,
    "hotelStars": "RV park",
    "hotelDescription": null,
    "checkInDate": "2026-06-07",
    "checkOutDate": "2026-06-08",
    "hotelAds": [],
    "popularTimesLiveText": null,
    "popularTimesLivePercent": null,
    "popularTimesHistogram": {},
    "openingHours": [],
    "peopleAlsoSearch": [],
    "placesTags": [],
    "reviewsTags": [],
    "additionalInfo": {
      "Service options": [
        {
          "Onsite services": true
        }
      ],
      "Accessibility": [
        {
          "Wheelchair accessible entrance": true
        },
        {
          "Wheelchair accessible parking lot": true
        },
        {
          "Wheelchair accessible restroom": true
        }
      ],
      "Offerings": [
        {
          "RV water hookup": true
        }
      ],
      "Payments": [
        {
          "Camping fee": true
        },
        {
          "Credit cards": true
        },
        {
          "Debit cards": true
        },
        {
          "NFC mobile payments": true
        },
        {
          "Credit cards": true
        }
      ],
      "Children": [
        {
          "Playground": true
        }
      ],
      "Pets": [
        {
          "Dogs allowed": true
        }
      ],
      "Amenities": [
        {
          "Free Wi-Fi": true
        }
      ]
    },
    "gasPrices": [],
    "url": "https://www.google.com/maps/search/?api=1&query=The%20Alpine%20Tourist%20Park%2C%20Adaminaby&query_place_id=ChIJHyYAkKcVPWsRxyRL4nAd6do",
    "searchPageUrl": "https://www.google.com/maps/search/caravan%20parks%20Snowy%20Mountains%20NSW?hl=en",
    "searchString": "caravan parks Snowy Mountains NSW",
    "language": "en",
    "rank": 10,
    "isAdvertisement": false,
    "imageUrl": "https://lh3.googleusercontent.com/gps-cs-s/APNQkAEHblprtvjTDu0CvERN8a86tXnJSLqNgBHhCaDMxZbaPqwJNjMX6Bic5th_oFScKJ23HMaYzTHepw483VvPs_o4ANV5HAO1PhWTrzOkeXAQrWOITnpwLnUOja-35J2gucGCIaoB=w408-h408-k-no",
    "kgmid": "/g/11bw4bzckv"
  },
  {
    "title": "Buckenderra Holiday Village",
    "subTitle": null,
    "description": null,
    "price": "$22",
    "categoryName": "RV park",
    "address": "490 Buckenderra Rd, Buckenderra NSW 2630, Australia",
    "neighborhood": null,
    "street": "490 Buckenderra Rd",
    "city": "Buckenderra",
    "postalCode": "2630",
    "state": "New South Wales",
    "countryCode": "AU",
    "website": "http://www.buckenderra.com.au/",
    "phone": "+61 1800 339 461",
    "phoneUnformatted": "",
    "claimThisBusiness": false,
    "location": {
      "lat": -36.1818122,
      "lng": 148.7646484
    },
    "locatedIn": null,
    "floor": null,
    "plusCode": null,
    "menu": null,
    "servicesLink": null,
    "totalScore": 4.3,
    "permanentlyClosed": false,
    "temporarilyClosed": false,
    "placeId": "ChIJ_72lfsYYPWsRnv-aZJTjwkk",
    "categories": [
      "RV park",
      "Campground",
      "Holiday park",
      "Tourist attraction"
    ],
    "fid": "0x6b3d18c67ea5bdff:0x49c2e394649aff9e",
    "cid": "5315060736733151134",
    "reviewsCount": 216,
    "imagesCount": 328,
    "imageCategories": [],
    "scrapedAt": "2026-05-26T04:12:46.169Z",
    "reserveTableUrl": null,
    "googleFoodUrl": null,
    "hotelStars": "3-star hotel",
    "hotelDescription": null,
    "checkInDate": "2026-06-07",
    "checkOutDate": "2026-06-08",
    "hotelAds": [],
    "popularTimesLiveText": null,
    "popularTimesLivePercent": null,
    "popularTimesHistogram": {},
    "openingHours": [],
    "peopleAlsoSearch": [],
    "placesTags": [],
    "reviewsTags": [],
    "additionalInfo": {
      "Service options": [
        {
          "Onsite services": true
        }
      ],
      "Accessibility": [
        {
          "Wheelchair accessible entrance": true
        },
        {
          "Wheelchair accessible parking lot": true
        },
        {
          "Wheelchair accessible restroom": true
        }
      ],
      "Offerings": [
        {
          "RV electric hookup": true
        }
      ],
      "Activities": [
        {
          "Hiking": true
        }
      ],
      "Payments": [
        {
          "Camping fee": true
        },
        {
          "Credit cards": true
        },
        {
          "Debit cards": true
        },
        {
          "NFC mobile payments": true
        },
        {
          "Credit cards": true
        }
      ],
      "Children": [
        {
          "Playground": true
        }
      ],
      "Parking": [
        {
          "Free parking lot": true
        }
      ],
      "Pets": [
        {
          "Dogs allowed": true
        }
      ]
    },
    "gasPrices": [],
    "url": "https://www.google.com/maps/search/?api=1&query=Buckenderra%20Holiday%20Village&query_place_id=ChIJ_72lfsYYPWsRnv-aZJTjwkk",
    "searchPageUrl": "https://www.google.com/maps/search/caravan%20parks%20Snowy%20Mountains%20NSW?hl=en",
    "searchString": "caravan parks Snowy Mountains NSW",
    "language": "en",
    "rank": 11,
    "isAdvertisement": false,
    "imageUrl": "https://dynamic-media-cdn.tripadvisor.com/media/photo-o/0d/b2/a4/32/photo0jpg.jpg?w=1900&h=1400&s=1",
    "kgmid": "/g/1th28krq"
  },
  {
    "title": "Khancoban Lakeside Caravan Park",
    "subTitle": null,
    "description": null,
    "price": null,
    "categoryName": "RV park",
    "address": "1362 Alpine Way, Khancoban NSW 2642, Australia",
    "neighborhood": null,
    "street": "1362 Alpine Way",
    "city": "Khancoban",
    "postalCode": "2642",
    "state": "New South Wales",
    "countryCode": "AU",
    "website": "https://www.klcp.com.au/",
    "phone": "+61 2 6076 9488",
    "phoneUnformatted": "+61260769488",
    "claimThisBusiness": false,
    "location": {
      "lat": -36.220062,
      "lng": 148.1205589
    },
    "locatedIn": null,
    "floor": null,
    "plusCode": null,
    "menu": null,
    "servicesLink": null,
    "totalScore": 4.4,
    "permanentlyClosed": false,
    "temporarilyClosed": false,
    "placeId": "ChIJlQOem78kI2sRs7G4BsqLnz4",
    "categories": [
      "RV park",
      "Campground",
      "Holiday park"
    ],
    "fid": "0x6b2324bf9b9e0395:0x3e9f8bca06b8b1b3",
    "cid": "4512479051460948403",
    "reviewsCount": 235,
    "imagesCount": 258,
    "imageCategories": [],
    "scrapedAt": "2026-05-26T04:12:46.169Z",
    "reserveTableUrl": null,
    "googleFoodUrl": null,
    "hotelStars": "RV park",
    "hotelDescription": null,
    "checkInDate": "2026-06-07",
    "checkOutDate": "2026-06-08",
    "hotelAds": [],
    "popularTimesLiveText": null,
    "popularTimesLivePercent": null,
    "popularTimesHistogram": {},
    "openingHours": [],
    "peopleAlsoSearch": [],
    "placesTags": [],
    "reviewsTags": [],
    "additionalInfo": {
      "Service options": [
        {
          "Onsite services": true
        }
      ],
      "Accessibility": [
        {
          "Wheelchair accessible entrance": true
        },
        {
          "Wheelchair accessible parking lot": true
        },
        {
          "Wheelchair accessible restroom": true
        }
      ],
      "Offerings": [
        {
          "RV electric hookup": true
        }
      ],
      "Payments": [
        {
          "Credit cards": true
        },
        {
          "Debit cards": true
        },
        {
          "NFC mobile payments": true
        }
      ],
      "Children": [
        {
          "Playground": true
        }
      ],
      "Pets": [
        {
          "Dogs allowed": true
        }
      ]
    },
    "gasPrices": [],
    "url": "https://www.google.com/maps/search/?api=1&query=Khancoban%20Lakeside%20Caravan%20Park&query_place_id=ChIJlQOem78kI2sRs7G4BsqLnz4",
    "searchPageUrl": "https://www.google.com/maps/search/caravan%20parks%20Snowy%20Mountains%20NSW?hl=en",
    "searchString": "caravan parks Snowy Mountains NSW",
    "language": "en",
    "rank": 12,
    "isAdvertisement": false,
    "imageUrl": "https://dynamic-media-cdn.tripadvisor.com/media/photo-o/0e/75/a6/09/spa-cabin.jpg?w=1300&h=800&s=1",
    "kgmid": "/g/1thd6vgf"
  },
  {
    "title": "Ngarigo Campground",
    "subTitle": null,
    "description": null,
    "price": null,
    "categoryName": "Campground",
    "address": "Alpine Way, Ngarigo NSW 2627, Australia",
    "neighborhood": null,
    "street": "Alpine Way",
    "city": "Ngarigo",
    "postalCode": "2627",
    "state": "NSW",
    "countryCode": "AU",
    "website": "https://www.nationalparks.nsw.gov.au/camping-and-accommodation/campgrounds/ngarigo-campground?utm_source=google&utm_medium=organic&utm_campaign=Google%20My%20Business&utm_term=plcid_7087170020581932948&utm_content=Ngarigo%20campground%20-%20Kosciuszko%20National%20Park",
    "phone": "+61 2 6450 5600",
    "phoneUnformatted": "+61264505600",
    "claimThisBusiness": false,
    "location": {
      "lat": -36.4587823,
      "lng": 148.3837987
    },
    "locatedIn": null,
    "floor": null,
    "plusCode": null,
    "menu": null,
    "servicesLink": null,
    "totalScore": 4.6,
    "permanentlyClosed": false,
    "temporarilyClosed": false,
    "placeId": "ChIJ47mUZLrKPGsR7RBDHr1DFkc",
    "categories": [
      "Campground"
    ],
    "fid": "0x6b3ccaba6494b9e3:0x471643bd1e4310ed",
    "cid": "5122356105716109549",
    "reviewsCount": 162,
    "imagesCount": 360,
    "imageCategories": [],
    "scrapedAt": "2026-05-26T04:12:46.169Z",
    "reserveTableUrl": null,
    "googleFoodUrl": null,
    "hotelStars": null,
    "hotelDescription": null,
    "checkInDate": null,
    "checkOutDate": null,
    "hotelAds": [],
    "popularTimesLiveText": null,
    "popularTimesLivePercent": null,
    "popularTimesHistogram": {},
    "openingHours": [],
    "peopleAlsoSearch": [],
    "placesTags": [],
    "reviewsTags": [],
    "additionalInfo": {
      "Accessibility": [
        {
          "Wheelchair accessible entrance": true
        },
        {
          "Wheelchair accessible parking lot": true
        }
      ],
      "Amenities": [
        {
          "Public restroom": true
        },
        {
          "Restroom": true
        },
        {
          "Running water": true
        },
        {
          "Tent sites": true
        }
      ],
      "Payments": [
        {
          "Camping fee": true
        }
      ]
    },
    "gasPrices": [],
    "url": "https://www.google.com/maps/search/?api=1&query=Ngarigo%20Campground&query_place_id=ChIJ47mUZLrKPGsR7RBDHr1DFkc",
    "searchPageUrl": "https://www.google.com/maps/search/caravan%20parks%20Snowy%20Mountains%20NSW?hl=en",
    "searchString": "caravan parks Snowy Mountains NSW",
    "language": "en",
    "rank": 13,
    "isAdvertisement": false,
    "imageUrl": "https://lh3.googleusercontent.com/gps-cs-s/APNQkAHyoEnTRO8Ilsl0AayFQdMMk7hh1N_T9J5niv7dc-x7nGbLnlUkBSs5CsMuBfS6t1Pj6TRdMGOcYnFvVm7Zz5ZvUCTDml8E2TK2neHsovhmfkA7DX2Hsxa_geizwlGqTAOEdl8t=w408-h544-k-no",
    "kgmid": "/g/12hmhwnw3"
  },
  {
    "title": "Yarrangobilly Village campground",
    "subTitle": null,
    "description": null,
    "price": null,
    "categoryName": "Campground",
    "address": "Snowy Mountains Highway, Yarrangobilly NSW 2720, Australia",
    "neighborhood": null,
    "street": "Snowy Mountains Highway",
    "city": "Yarrangobilly",
    "postalCode": "2720",
    "state": "NSW",
    "countryCode": "AU",
    "website": "https://www.nationalparks.nsw.gov.au/camping-and-accommodation/campgrounds/yarrangobilly-village-campground?utm_source=google&utm_medium=organic&utm_campaign=Google+My+Business+Page&utm_term=plcid_1087433870937707443&utm_content=Yarrangobilly%20Village%20campground%20-%20Yarrangobilly",
    "phone": "+61 2 6947 7025",
    "phoneUnformatted": "+61269477025",
    "claimThisBusiness": false,
    "location": {
      "lat": -35.6520104,
      "lng": 148.4622436
    },
    "locatedIn": null,
    "floor": null,
    "plusCode": null,
    "menu": null,
    "servicesLink": null,
    "totalScore": 4.5,
    "permanentlyClosed": false,
    "temporarilyClosed": false,
    "placeId": "ChIJTZV0799TPWsRzk0xobC48Ug",
    "categories": [
      "Campground"
    ],
    "fid": "0x6b3d53dfef74954d:0x48f1b8b0a1314dce",
    "cid": "5256185308876197326",
    "reviewsCount": 109,
    "imagesCount": 456,
    "imageCategories": [],
    "scrapedAt": "2026-05-26T04:12:46.169Z",
    "reserveTableUrl": null,
    "googleFoodUrl": null,
    "hotelStars": null,
    "hotelDescription": null,
    "checkInDate": null,
    "checkOutDate": null,
    "hotelAds": [],
    "popularTimesLiveText": null,
    "popularTimesLivePercent": null,
    "popularTimesHistogram": {},
    "openingHours": [],
    "peopleAlsoSearch": [],
    "placesTags": [],
    "reviewsTags": [],
    "additionalInfo": {
      "Accessibility": [
        {
          "Wheelchair accessible entrance": true
        },
        {
          "Wheelchair accessible parking lot": true
        }
      ],
      "Offerings": [
        {
          "RV camping": true
        },
        {
          "RV sewer hookup": true
        }
      ],
      "Amenities": [
        {
          "Public restroom": true
        },
        {
          "Restroom": true
        },
        {
          "Running water": true
        },
        {
          "Tent sites": true
        }
      ]
    },
    "gasPrices": [],
    "url": "https://www.google.com/maps/search/?api=1&query=Yarrangobilly%20Village%20campground&query_place_id=ChIJTZV0799TPWsRzk0xobC48Ug",
    "searchPageUrl": "https://www.google.com/maps/search/caravan%20parks%20Snowy%20Mountains%20NSW?hl=en",
    "searchString": "caravan parks Snowy Mountains NSW",
    "language": "en",
    "rank": 14,
    "isAdvertisement": false,
    "imageUrl": "https://lh3.googleusercontent.com/gps-cs-s/APNQkAGCRgyDntyFzkHmuC_gA_pDKqEiYlbqUrTg2yV6J8jds7cXiYS9fqacboGY3xYbjh1SOVbDVID0HbSkjPPRZ_rpw1bGp1OXmjtxvmqfI5ekD0EvXzt4gF-L8fduBlB3F9qfI1YhLQ=w426-h240-k-no",
    "kgmid": "/g/11cmsw46np"
  },
  {
    "title": "Providence Park",
    "subTitle": null,
    "description": null,
    "price": "$222",
    "categoryName": "Holiday park",
    "address": "46 Providence Rd, Providence Portal NSW 2630, Australia",
    "neighborhood": null,
    "street": "46 Providence Rd",
    "city": "Providence Portal",
    "postalCode": "2630",
    "state": "New South Wales",
    "countryCode": "AU",
    "website": "https://providence-park.au/",
    "phone": "+61 2 6454 2357",
    "phoneUnformatted": "+61264542357",
    "claimThisBusiness": false,
    "location": {
      "lat": -35.942838,
      "lng": 148.6270919
    },
    "locatedIn": null,
    "floor": null,
    "plusCode": null,
    "menu": null,
    "servicesLink": null,
    "totalScore": 4.5,
    "permanentlyClosed": false,
    "temporarilyClosed": false,
    "placeId": "ChIJ99XJusM4PWsRNjvokETizC0",
    "categories": [
      "Holiday park"
    ],
    "fid": "0x6b3d38c3bac9d5f7:0x2dcce24490e83b36",
    "cid": "3300261411072523062",
    "reviewsCount": 48,
    "imagesCount": 93,
    "imageCategories": [],
    "scrapedAt": "2026-05-26T04:12:46.169Z",
    "reserveTableUrl": null,
    "googleFoodUrl": null,
    "hotelStars": "Holiday park",
    "hotelDescription": null,
    "checkInDate": "2026-06-07",
    "checkOutDate": "2026-06-08",
    "hotelAds": [],
    "popularTimesLiveText": null,
    "popularTimesLivePercent": null,
    "popularTimesHistogram": {},
    "openingHours": [],
    "peopleAlsoSearch": [],
    "placesTags": [],
    "reviewsTags": [],
    "additionalInfo": {
      "Amenities": [
        {
          "Free Wi-Fi": true
        }
      ]
    },
    "gasPrices": [],
    "url": "https://www.google.com/maps/search/?api=1&query=Providence%20Park&query_place_id=ChIJ99XJusM4PWsRNjvokETizC0",
    "searchPageUrl": "https://www.google.com/maps/search/caravan%20parks%20Snowy%20Mountains%20NSW?hl=en",
    "searchString": "caravan parks Snowy Mountains NSW",
    "language": "en",
    "rank": 15,
    "isAdvertisement": false,
    "imageUrl": "https://lh3.googleusercontent.com/gps-cs-s/APNQkAGVR3b5UOETLzwn3rewbchKeV9p3ev74OTV1mofIyku8lDhSjWwJ-_kfAGh54dAn2K9Cdxvtu-venBfwocbjKXXNCQ505hvBDubsLGg8WTvJNxj-eQnfpi8OZRtV6LERg0NMAjRWQ=w408-h272-k-no",
    "kgmid": "/g/1tctxqpp"
  },
  {
    "title": "Talbingo Caravan Park",
    "subTitle": null,
    "description": null,
    "price": null,
    "categoryName": "RV park",
    "address": "24 Whitty St, Talbingo NSW 2720, Australia",
    "neighborhood": null,
    "street": "24 Whitty St",
    "city": "Talbingo",
    "postalCode": "2720",
    "state": "New South Wales",
    "countryCode": "AU",
    "website": "http://www.talbingocaravanpark.com.au/",
    "phone": "+61 2 6949 5239",
    "phoneUnformatted": "+61269495239",
    "claimThisBusiness": false,
    "location": {
      "lat": -35.5838153,
      "lng": 148.2931352
    },
    "locatedIn": null,
    "floor": null,
    "plusCode": null,
    "menu": null,
    "servicesLink": null,
    "totalScore": 4.5,
    "permanentlyClosed": false,
    "temporarilyClosed": false,
    "placeId": "ChIJ-wZk5gmsImsR0t9ZLted8eg",
    "categories": [
      "RV park"
    ],
    "fid": "0x6b22ac09e66406fb:0xe8f19dd72e59dfd2",
    "cid": "16785370833707720658",
    "reviewsCount": 181,
    "imagesCount": 301,
    "imageCategories": [],
    "scrapedAt": "2026-05-26T04:12:46.170Z",
    "reserveTableUrl": null,
    "googleFoodUrl": null,
    "hotelStars": "RV park",
    "hotelDescription": null,
    "checkInDate": "2026-06-07",
    "checkOutDate": "2026-06-08",
    "hotelAds": [],
    "popularTimesLiveText": null,
    "popularTimesLivePercent": null,
    "popularTimesHistogram": {},
    "openingHours": [],
    "peopleAlsoSearch": [],
    "placesTags": [],
    "reviewsTags": [],
    "additionalInfo": {
      "Service options": [
        {
          "Onsite services": true
        }
      ],
      "Accessibility": [
        {
          "Wheelchair accessible entrance": true
        },
        {
          "Wheelchair accessible parking lot": true
        },
        {
          "Wheelchair accessible restroom": true
        }
      ],
      "Offerings": [
        {
          "RV camping": true
        },
        {
          "RV electric hookup": true
        }
      ],
      "Payments": [
        {
          "Camping fee": true
        },
        {
          "Credit cards": true
        },
        {
          "Debit cards": true
        },
        {
          "NFC mobile payments": true
        },
        {
          "Credit cards": true
        }
      ],
      "Children": [
        {
          "Playground": true
        }
      ],
      "Pets": [
        {
          "Dogs allowed": true
        }
      ],
      "Amenities": [
        {
          "Free Wi-Fi": true
        }
      ]
    },
    "gasPrices": [],
    "url": "https://www.google.com/maps/search/?api=1&query=Talbingo%20Caravan%20Park&query_place_id=ChIJ-wZk5gmsImsR0t9ZLted8eg",
    "searchPageUrl": "https://www.google.com/maps/search/caravan%20parks%20Snowy%20Mountains%20NSW?hl=en",
    "searchString": "caravan parks Snowy Mountains NSW",
    "language": "en",
    "rank": 16,
    "isAdvertisement": false,
    "imageUrl": "https://dynamic-media-cdn.tripadvisor.com/media/photo-o/16/3a/e6/6c/photo0jpg.jpg?w=1900&h=1400&s=1",
    "kgmid": "/g/1v5k357g"
  },
  {
    "title": "Tumut Valley Holiday Park",
    "subTitle": null,
    "description": null,
    "price": null,
    "categoryName": "RV park",
    "address": "509-511 Snowy Mountains Hwy, Tumut NSW 2720, Australia",
    "neighborhood": null,
    "street": "509-511 Snowy Mountains Hwy",
    "city": "Tumut",
    "postalCode": "2720",
    "state": "New South Wales",
    "countryCode": "AU",
    "website": "https://www.tvhp.com.au/",
    "phone": "+61 1300 473 002",
    "phoneUnformatted": "",
    "claimThisBusiness": false,
    "location": {
      "lat": -35.3418285,
      "lng": 148.2464534
    },
    "locatedIn": null,
    "floor": null,
    "plusCode": null,
    "menu": null,
    "servicesLink": null,
    "totalScore": 4.2,
    "permanentlyClosed": false,
    "temporarilyClosed": false,
    "placeId": "ChIJ4efWCdAEGGsRppKdOk9D41o",
    "categories": [
      "RV park",
      "Campground",
      "Holiday park",
      "Motel"
    ],
    "fid": "0x6b1804d009d6e7e1:0x5ae3434f3a9d92a6",
    "cid": "6549152290691715750",
    "reviewsCount": 108,
    "imagesCount": 163,
    "imageCategories": [],
    "scrapedAt": "2026-05-26T04:12:46.170Z",
    "reserveTableUrl": null,
    "googleFoodUrl": null,
    "hotelStars": "RV park",
    "hotelDescription": null,
    "checkInDate": "2026-06-07",
    "checkOutDate": "2026-06-08",
    "hotelAds": [],
    "popularTimesLiveText": null,
    "popularTimesLivePercent": null,
    "popularTimesHistogram": {},
    "openingHours": [],
    "peopleAlsoSearch": [],
    "placesTags": [],
    "reviewsTags": [],
    "additionalInfo": {
      "Service options": [
        {
          "Onsite services": true
        }
      ],
      "Accessibility": [
        {
          "Assistive hearing loop": false
        },
        {
          "Wheelchair accessible entrance": false
        },
        {
          "Wheelchair accessible parking lot": false
        },
        {
          "Wheelchair accessible restroom": false
        },
        {
          "Wheelchair accessible seating": false
        }
      ],
      "Offerings": [
        {
          "RV camping": true
        },
        {
          "RV electric hookup": true
        },
        {
          "RV sewer hookup": true
        },
        {
          "RV water hookup": true
        }
      ],
      "Activities": [
        {
          "Hiking": true
        }
      ],
      "Payments": [
        {
          "Camping fee": true
        },
        {
          "Credit cards": true
        },
        {
          "Debit cards": true
        },
        {
          "NFC mobile payments": true
        },
        {
          "Credit cards": true
        }
      ],
      "Children": [
        {
          "Playground": true
        }
      ],
      "Parking": [
        {
          "On-site parking": true
        }
      ],
      "Pets": [
        {
          "Dogs allowed": true
        }
      ]
    },
    "gasPrices": [],
    "url": "https://www.google.com/maps/search/?api=1&query=Tumut%20Valley%20Holiday%20Park&query_place_id=ChIJ4efWCdAEGGsRppKdOk9D41o",
    "searchPageUrl": "https://www.google.com/maps/search/caravan%20parks%20Snowy%20Mountains%20NSW?hl=en",
    "searchString": "caravan parks Snowy Mountains NSW",
    "language": "en",
    "rank": 17,
    "isAdvertisement": false,
    "imageUrl": "https://lh3.googleusercontent.com/gps-cs-s/APNQkAExB8XfBNseCZux82BCra4g7nyRm7K83a5HmmI9VlYLoZPaOSk0zZCH50NFmfIkGHiiEvKuppzXqlsyYzpkDD-ecZwDeeI3enCJIK-UwvW3TV6349o7C7-KnEe8wvHqZxlLQ9Uu8IuEz84=w408-h306-k-no",
    "kgmid": "/g/11c0pzqcq3"
  },
  {
    "title": "Reflections Tumut River - Holiday Park",
    "subTitle": null,
    "description": null,
    "price": null,
    "categoryName": "RV park",
    "address": "2 Fitzroy St, Tumut NSW 2720, Australia",
    "neighborhood": null,
    "street": "2 Fitzroy St",
    "city": "Tumut",
    "postalCode": "2720",
    "state": "New South Wales",
    "countryCode": "AU",
    "website": "https://reflectionsholidays.com.au/parks/tumut-river/?utm_source=gmb-listing&utm_medium=tumutriver&utm_campaign=maps-listing",
    "phone": "+61 2 5973 0029",
    "phoneUnformatted": "+61259730029",
    "claimThisBusiness": false,
    "location": {
      "lat": -35.2947005,
      "lng": 148.2198133
    },
    "locatedIn": null,
    "floor": null,
    "plusCode": null,
    "menu": null,
    "servicesLink": null,
    "totalScore": 4.4,
    "permanentlyClosed": false,
    "temporarilyClosed": false,
    "placeId": "ChIJsUztKtUEGGsRze9F4yxOIps",
    "categories": [
      "RV park",
      "Campground",
      "Holiday park"
    ],
    "fid": "0x6b1804d52aed4cb1:0x9b224e2ce345efcd",
    "cid": "11178583179785531341",
    "reviewsCount": 634,
    "imagesCount": 1028,
    "imageCategories": [],
    "scrapedAt": "2026-05-26T04:13:57.908Z",
    "reserveTableUrl": null,
    "googleFoodUrl": null,
    "hotelStars": "2-star hotel",
    "hotelDescription": null,
    "checkInDate": "2026-06-07",
    "checkOutDate": "2026-06-08",
    "hotelAds": [],
    "popularTimesLiveText": null,
    "popularTimesLivePercent": null,
    "popularTimesHistogram": {},
    "openingHours": [],
    "peopleAlsoSearch": [],
    "placesTags": [],
    "reviewsTags": [],
    "additionalInfo": {
      "Service options": [
        {
          "Onsite services": true
        }
      ],
      "Accessibility": [
        {
          "Wheelchair accessible entrance": true
        },
        {
          "Wheelchair accessible parking lot": true
        },
        {
          "Wheelchair accessible restroom": true
        }
      ],
      "Offerings": [
        {
          "RV camping": true
        },
        {
          "RV electric hookup": true
        },
        {
          "RV water hookup": true
        }
      ],
      "Activities": [
        {
          "Hiking": true
        }
      ],
      "Payments": [
        {
          "Camping fee": true
        },
        {
          "Credit cards": true
        },
        {
          "Debit cards": true
        },
        {
          "NFC mobile payments": true
        },
        {
          "Credit cards": true
        }
      ],
      "Children": [
        {
          "Playground": true
        }
      ],
      "Pets": [
        {
          "Dogs allowed": true
        }
      ]
    },
    "gasPrices": [],
    "url": "https://www.google.com/maps/search/?api=1&query=Reflections%20Tumut%20River%20-%20Holiday%20Park&query_place_id=ChIJsUztKtUEGGsRze9F4yxOIps",
    "searchPageUrl": "https://www.google.com/maps/search/caravan%20park%20Snowy%20Mountains%20NSW?hl=en",
    "searchString": "caravan park Snowy Mountains NSW",
    "language": "en",
    "rank": 14,
    "isAdvertisement": false,
    "imageUrl": "https://lh3.googleusercontent.com/gps-cs-s/APNQkAGfnUEOL4hyo-_4PXkslrZ0cnlxss00psd6gRMVT-p9v1g7nt9x0gTMomAdaF-ru6Ww-dRtKKcxhWo8t1RSCjI-8xUw5uNgc8k26JmkdcoofEZBr-sq_6yMpxgug8UUEEV8uf3zbKGKKfj9=w408-h272-k-no",
    "kgmid": "/g/1trpqz52"
  },
  {
    "title": "Snowy Mountains Farm Stay",
    "subTitle": null,
    "description": null,
    "price": null,
    "categoryName": "Farmstay",
    "address": "1389 Paupong Rd, Paupong NSW 2628, Australia",
    "neighborhood": null,
    "street": "1389 Paupong Rd",
    "city": "Paupong",
    "postalCode": "2628",
    "state": "New South Wales",
    "countryCode": "AU",
    "website": "http://www.snowyfarmstay.com.au/",
    "phone": "+61 2 4455 5444",
    "phoneUnformatted": "+61244555444",
    "claimThisBusiness": false,
    "location": {
      "lat": -36.6541954,
      "lng": 148.6959572
    },
    "locatedIn": null,
    "floor": null,
    "plusCode": null,
    "menu": null,
    "servicesLink": null,
    "totalScore": 5,
    "permanentlyClosed": false,
    "temporarilyClosed": false,
    "placeId": "ChIJmy52IBa9PGsRt_J12r474_c",
    "categories": [
      "Farmstay"
    ],
    "fid": "0x6b3cbd1620762e9b:0xf7e33bbeda75f2b7",
    "cid": "17862186237976507063",
    "reviewsCount": 4,
    "imagesCount": 22,
    "imageCategories": [],
    "scrapedAt": "2026-05-26T04:13:57.909Z",
    "reserveTableUrl": null,
    "googleFoodUrl": null,
    "hotelStars": null,
    "hotelDescription": null,
    "checkInDate": null,
    "checkOutDate": null,
    "hotelAds": [],
    "popularTimesLiveText": null,
    "popularTimesLivePercent": null,
    "popularTimesHistogram": {},
    "openingHours": [],
    "peopleAlsoSearch": [],
    "placesTags": [],
    "reviewsTags": [],
    "gasPrices": [],
    "url": "https://www.google.com/maps/search/?api=1&query=Snowy%20Mountains%20Farm%20Stay&query_place_id=ChIJmy52IBa9PGsRt_J12r474_c",
    "searchPageUrl": "https://www.google.com/maps/search/caravan%20park%20Snowy%20Mountains%20NSW?hl=en",
    "searchString": "caravan park Snowy Mountains NSW",
    "language": "en",
    "rank": 16,
    "isAdvertisement": false,
    "imageUrl": "https://lh3.googleusercontent.com/gps-cs-s/APNQkAF2HWkR9HH0dFc6vUTaBxgepcTpdp9hLoRgmOZpz_RWKZqtGqn4hoA37PnKKz5-sWBslQ0Zj_99p1xm4Im7fTIHH2YKevF0a0k6FDSeqMzG2AqNlmQi60M0tP97fxQenq7D0-oDGijgQu3Z=w408-h306-k-no",
    "kgmid": "/g/11ldczbgx_"
  },
  {
    "title": "Pinch River - Moyangul campground",
    "subTitle": null,
    "description": null,
    "price": null,
    "categoryName": "Campground",
    "address": "Horseshoe Camping Area Access, Ingeegoodbee NSW 2627, Australia",
    "neighborhood": null,
    "street": "Horseshoe Camping Area Access",
    "city": "Ingeegoodbee",
    "postalCode": "2627",
    "state": "New South Wales",
    "countryCode": "AU",
    "website": "https://www.nationalparks.nsw.gov.au/camping-and-accommodation/campgrounds/pinch-river-moyangul-campground?utm_source=google&utm_medium=organic&utm_campaign=Google%20My%20Business%20Page&utm_term=plcid_11379345967306390770&utm_content=Pinch%20River%20-%20Moyangul%20campground%20-%20Kosciuszko%20National%20Park",
    "phone": "+61 2 6450 5600",
    "phoneUnformatted": "+61264505600",
    "claimThisBusiness": false,
    "location": {
      "lat": -36.792468,
      "lng": 148.4072167
    },
    "locatedIn": null,
    "floor": null,
    "plusCode": null,
    "menu": null,
    "servicesLink": null,
    "totalScore": 4.1,
    "permanentlyClosed": false,
    "temporarilyClosed": false,
    "placeId": "ChIJueDH3XxVO2sRVZ-5jukMQAU",
    "categories": [
      "Campground"
    ],
    "fid": "0x6b3b557cddc7e0b9:0x5400ce98eb99f55",
    "cid": "378316565960564565",
    "reviewsCount": 22,
    "imagesCount": 42,
    "imageCategories": [],
    "scrapedAt": "2026-05-26T04:13:57.909Z",
    "reserveTableUrl": null,
    "googleFoodUrl": null,
    "hotelStars": null,
    "hotelDescription": null,
    "checkInDate": null,
    "checkOutDate": null,
    "hotelAds": [],
    "popularTimesLiveText": null,
    "popularTimesLivePercent": null,
    "popularTimesHistogram": {},
    "openingHours": [],
    "peopleAlsoSearch": [],
    "placesTags": [],
    "reviewsTags": [],
    "additionalInfo": {
      "Accessibility": [
        {
          "Wheelchair accessible entrance": false
        }
      ],
      "Amenities": [
        {
          "Public restroom": true
        },
        {
          "Running water": true
        },
        {
          "Tent sites": true
        }
      ]
    },
    "gasPrices": [],
    "url": "https://www.google.com/maps/search/?api=1&query=Pinch%20River%20-%20Moyangul%20campground&query_place_id=ChIJueDH3XxVO2sRVZ-5jukMQAU",
    "searchPageUrl": "https://www.google.com/maps/search/caravan%20park%20Snowy%20Mountains%20NSW?hl=en",
    "searchString": "caravan park Snowy Mountains NSW",
    "language": "en",
    "rank": 19,
    "isAdvertisement": false,
    "imageUrl": "https://lh3.googleusercontent.com/gps-cs-s/APNQkAEkdFQ6tcyQDgbzFIJoR-_9_dlhciiCIqjCROUf3CeyvItkDfZN8xBHmqJlae0RwUZwUA40LsXQpRp6J0bwcQYoCK1TiszP1sA3iM-GJ_EjXGDuZXkoqqmq5nTrOdSfL5VxKja3=w408-h306-k-no",
    "kgmid": "/g/11cmdg20sp"
  },
  {
    "title": "Snowy Mountains",
    "subTitle": null,
    "description": "Highest mountain range in Australia topping out at 7,310 ft., with ski resorts & alpine lakes.",
    "price": null,
    "categoryName": "Mountain range",
    "address": "Jacobs River NSW 2627, Australia",
    "neighborhood": null,
    "street": null,
    "city": "Jacobs River",
    "postalCode": null,
    "state": "New South Wales",
    "countryCode": "AU",
    "phone": "",
    "phoneUnformatted": "",
    "claimThisBusiness": false,
    "location": {
      "lat": -36.5,
      "lng": 148.3333333
    },
    "locatedIn": null,
    "floor": null,
    "plusCode": null,
    "menu": null,
    "servicesLink": null,
    "totalScore": 4.5,
    "permanentlyClosed": false,
    "temporarilyClosed": false,
    "placeId": "ChIJXd3yjANLI2sRuGHX-F-UI14",
    "categories": [
      "Mountain range"
    ],
    "fid": "0x6b234b038cf2dd5d:0x5e23945ff8d761b8",
    "cid": "6783428603667767736",
    "reviewsCount": 356,
    "imagesCount": 1579,
    "imageCategories": [],
    "scrapedAt": "2026-05-26T04:13:57.909Z",
    "reserveTableUrl": null,
    "googleFoodUrl": null,
    "hotelStars": null,
    "hotelDescription": null,
    "checkInDate": null,
    "checkOutDate": null,
    "hotelAds": [],
    "popularTimesLiveText": null,
    "popularTimesLivePercent": null,
    "popularTimesHistogram": {},
    "openingHours": [],
    "peopleAlsoSearch": [],
    "placesTags": [],
    "reviewsTags": [],
    "gasPrices": [],
    "url": "https://www.google.com/maps/search/?api=1&query=Snowy%20Mountains&query_place_id=ChIJXd3yjANLI2sRuGHX-F-UI14",
    "searchPageUrl": "https://www.google.com/maps/search/caravan%20park%20Snowy%20Mountains%20NSW?hl=en",
    "searchString": "caravan park Snowy Mountains NSW",
    "language": "en",
    "rank": 20,
    "isAdvertisement": false,
    "imageUrl": "https://lh3.googleusercontent.com/gps-cs-s/APNQkAGjHf5CLp1gtkYlhi0Yb5h36qPVC-F1vDUOTR-JqKDu11mkCRwz8XJjl4lXjFHNrMrir1duwQJBf6TvR9BxFGa3ZG8vNtLZYgee_UWsXYmfQ_ugWXTI70gqWnrwPdVmtlmfbx3H=w408-h306-k-no",
    "kgmid": "/m/074wm"
  },
  {
    "title": "Snowy Mountain Resort",
    "subTitle": null,
    "description": null,
    "price": "NOK 1,658",
    "categoryName": "Motel",
    "address": "1 Lucas St, Adaminaby NSW 2629, Australia",
    "neighborhood": null,
    "street": "1 Lucas St",
    "city": "Adaminaby",
    "postalCode": "2629",
    "state": "New South Wales",
    "countryCode": "AU",
    "website": "https://snowymountains.com.au/",
    "phone": "+61 2 6454 2380",
    "phoneUnformatted": "+61264542380",
    "claimThisBusiness": false,
    "location": {
      "lat": -35.9963018,
      "lng": 148.7809647
    },
    "locatedIn": null,
    "floor": null,
    "plusCode": null,
    "menu": null,
    "servicesLink": null,
    "totalScore": 3.7,
    "permanentlyClosed": false,
    "temporarilyClosed": false,
    "placeId": "ChIJEUv7CgEVPWsRVGPBI1BjV_g",
    "categories": [
      "Motel"
    ],
    "fid": "0x6b3d15010afb4b11:0xf857635023c16354",
    "cid": "17894880840228365140",
    "reviewsCount": 139,
    "imagesCount": 127,
    "imageCategories": [],
    "scrapedAt": "2026-05-26T04:15:07.954Z",
    "reserveTableUrl": null,
    "googleFoodUrl": null,
    "hotelStars": "3-star hotel",
    "hotelDescription": null,
    "checkInDate": "2026-06-07",
    "checkOutDate": "2026-06-08",
    "hotelAds": [],
    "popularTimesLiveText": null,
    "popularTimesLivePercent": null,
    "popularTimesHistogram": {},
    "openingHours": [],
    "peopleAlsoSearch": [],
    "placesTags": [],
    "reviewsTags": [],
    "additionalInfo": {
      "Amenities": [
        {
          "Free Wi-Fi": true
        }
      ]
    },
    "gasPrices": [],
    "url": "https://www.google.com/maps/search/?api=1&query=Snowy%20Mountain%20Resort&query_place_id=ChIJEUv7CgEVPWsRVGPBI1BjV_g",
    "searchPageUrl": "https://www.google.com/maps/search/tourist%20park%20Snowy%20Mountains%20NSW?hl=en",
    "searchString": "tourist park Snowy Mountains NSW",
    "language": "en",
    "rank": 9,
    "isAdvertisement": false,
    "imageUrl": "https://lh3.googleusercontent.com/gps-cs-s/APNQkAFhAY9crxdg14d7aDD5OxuA_-uo046wM1LRpT0G5fB18qD8rVUcWdqF4brQvVZUKT7likbnp8kvyjAzlAYKRD1zn6fuDtznNWmmj43hgOS3sqLraEaTouO1KDWUm_B7Qtp9ZEepYQ=w927-h240-k-no",
    "kgmid": "/g/1v_vt1ww"
  },
  {
    "title": "Snowy Mountains Highway",
    "subTitle": null,
    "description": null,
    "price": null,
    "categoryName": "Tourist attraction",
    "address": "Kosciuszko National Park, Selwyn area in, Broken Dam NSW 2629, Australia",
    "neighborhood": null,
    "street": "Kosciuszko National Park, Selwyn area in",
    "city": "Broken Dam",
    "postalCode": "2629",
    "state": "NSW",
    "countryCode": "AU",
    "website": "https://www.nationalparks.nsw.gov.au/things-to-do/driving-routes/snowy-mountains-highway?utm_source=google&utm_medium=organic&utm_campaign=Google%20My%20Business%20Page&utm_term=plcid_8371787729536529421&utm_content=Snowy%20Mountains%20Highway%20-%20Kosciuszko%20National%20Park",
    "phone": "+61 2 6947 7025",
    "phoneUnformatted": "+61269477025",
    "claimThisBusiness": false,
    "location": {
      "lat": -35.9093669,
      "lng": 148.5614885
    },
    "locatedIn": null,
    "floor": null,
    "plusCode": null,
    "menu": null,
    "servicesLink": null,
    "totalScore": 5,
    "permanentlyClosed": false,
    "temporarilyClosed": false,
    "placeId": "ChIJeTtJr145PWsRmV5njFbK9es",
    "categories": [
      "Tourist attraction"
    ],
    "fid": "0x6b3d395eaf493b79:0xebf5ca568c675e99",
    "cid": "17002718441278758553",
    "reviewsCount": 14,
    "imagesCount": 58,
    "imageCategories": [],
    "scrapedAt": "2026-05-26T04:15:07.954Z",
    "reserveTableUrl": null,
    "googleFoodUrl": null,
    "hotelStars": null,
    "hotelDescription": null,
    "checkInDate": null,
    "checkOutDate": null,
    "hotelAds": [],
    "popularTimesLiveText": null,
    "popularTimesLivePercent": null,
    "popularTimesHistogram": {},
    "openingHours": [],
    "peopleAlsoSearch": [],
    "placesTags": [],
    "reviewsTags": [],
    "additionalInfo": {
      "Planning": [
        {
          "Getting tickets in advance recommended": true
        }
      ],
      "Children": [
        {
          "Good for kids": true
        }
      ]
    },
    "gasPrices": [],
    "url": "https://www.google.com/maps/search/?api=1&query=Snowy%20Mountains%20Highway&query_place_id=ChIJeTtJr145PWsRmV5njFbK9es",
    "searchPageUrl": "https://www.google.com/maps/search/tourist%20park%20Snowy%20Mountains%20NSW?hl=en",
    "searchString": "tourist park Snowy Mountains NSW",
    "language": "en",
    "rank": 10,
    "isAdvertisement": false,
    "imageUrl": "https://lh3.googleusercontent.com/gps-cs-s/APNQkAEGfx9JcTNk9cHvU4mlznSgq5YhjZB0j6iwL8tSe8xwfnayz8AvhR5oLkK7Fo376XScJmB6FHkEItP_FiF_rW8zzMtEAyTEv4mqEbBVSfQkAlir8kSdkfcS1-U55DdBT7Swa5A=w408-h270-k-no",
    "kgmid": "/g/11rsqz55q4"
  },
  {
    "title": "Snowy Mountains Alpine Cottages",
    "subTitle": null,
    "description": null,
    "price": null,
    "categoryName": "Cottage",
    "address": "6076 Snowy Mountains Hwy, Adaminaby NSW 2629, Australia",
    "neighborhood": null,
    "street": "6076 Snowy Mountains Hwy",
    "city": "Adaminaby",
    "postalCode": "2629",
    "state": "New South Wales",
    "countryCode": "AU",
    "website": "http://adaminabycottages.com.au/",
    "phone": "+61 2 6454 1120",
    "phoneUnformatted": "+61264541120",
    "claimThisBusiness": true,
    "location": {
      "lat": -35.9616227,
      "lng": 148.7026549
    },
    "locatedIn": null,
    "floor": null,
    "plusCode": null,
    "menu": null,
    "servicesLink": null,
    "totalScore": 4.5,
    "permanentlyClosed": false,
    "temporarilyClosed": false,
    "placeId": "ChIJydJrmKY_PWsR8j97YI9tj-g",
    "categories": [
      "Cottage",
      "Mountain cabin"
    ],
    "fid": "0x6b3d3fa6986bd2c9:0xe88f6d8f607b3ff2",
    "cid": "16757733201035345906",
    "reviewsCount": 24,
    "imagesCount": 29,
    "imageCategories": [],
    "scrapedAt": "2026-05-26T04:15:07.954Z",
    "reserveTableUrl": null,
    "googleFoodUrl": null,
    "hotelStars": "Cottage",
    "hotelDescription": null,
    "checkInDate": "2026-06-07",
    "checkOutDate": "2026-06-08",
    "hotelAds": [],
    "popularTimesLiveText": null,
    "popularTimesLivePercent": null,
    "popularTimesHistogram": {},
    "openingHours": [],
    "peopleAlsoSearch": [],
    "placesTags": [],
    "reviewsTags": [],
    "gasPrices": [],
    "url": "https://www.google.com/maps/search/?api=1&query=Snowy%20Mountains%20Alpine%20Cottages&query_place_id=ChIJydJrmKY_PWsR8j97YI9tj-g",
    "searchPageUrl": "https://www.google.com/maps/search/tourist%20park%20Snowy%20Mountains%20NSW?hl=en",
    "searchString": "tourist park Snowy Mountains NSW",
    "language": "en",
    "rank": 11,
    "isAdvertisement": false,
    "imageUrl": "https://dynamic-media-cdn.tripadvisor.com/media/photo-o/05/32/dc/63/snowy-mountains-alpine.jpg?w=1900&h=1400&s=1",
    "kgmid": "/g/1tcvc1fg"
  },
  {
    "title": "Yachting Point campground",
    "subTitle": null,
    "description": null,
    "price": null,
    "categoryName": "Campground",
    "address": "Snowy Mountains Hwy Tumut area in Kosciuszko National Park, Blowering NSW 2720, Australia",
    "neighborhood": null,
    "street": "Snowy Mountains Hwy Tumut area in Kosciuszko National Park",
    "city": "Blowering",
    "postalCode": "2720",
    "state": "NSW",
    "countryCode": "AU",
    "website": "https://www.nationalparks.nsw.gov.au/camping-and-accommodation/campgrounds/yachting-point-campground?utm_source=google&utm_medium=organic&utm_campaign=Google+My+Business+Page&utm_term=plcid_7765479645060201834&utm_content=Yachting%20Point%20campground%20-%20Blowering",
    "phone": "+61 1300 072 757",
    "phoneUnformatted": "",
    "claimThisBusiness": false,
    "location": {
      "lat": -35.5106469,
      "lng": 148.2678404
    },
    "locatedIn": null,
    "floor": null,
    "plusCode": null,
    "menu": null,
    "servicesLink": null,
    "totalScore": 4.3,
    "permanentlyClosed": false,
    "temporarilyClosed": false,
    "placeId": "ChIJ1yDlDq6pImsRZ3GndUhtIQ0",
    "categories": [
      "Campground"
    ],
    "fid": "0x6b22a9ae0ee520d7:0xd216d4875a77167",
    "cid": "946157554703495527",
    "reviewsCount": 43,
    "imagesCount": 173,
    "imageCategories": [],
    "scrapedAt": "2026-05-26T04:15:07.954Z",
    "reserveTableUrl": null,
    "googleFoodUrl": null,
    "hotelStars": null,
    "hotelDescription": null,
    "checkInDate": null,
    "checkOutDate": null,
    "hotelAds": [],
    "popularTimesLiveText": null,
    "popularTimesLivePercent": null,
    "popularTimesHistogram": {},
    "openingHours": [],
    "peopleAlsoSearch": [],
    "placesTags": [],
    "reviewsTags": [],
    "additionalInfo": {
      "Accessibility": [
        {
          "Wheelchair accessible parking lot": true
        }
      ],
      "Offerings": [
        {
          "RV camping": true
        }
      ],
      "Amenities": [
        {
          "Public restroom": true
        },
        {
          "Restroom": true
        },
        {
          "Running water": true
        },
        {
          "Tent sites": true
        }
      ],
      "Payments": [
        {
          "Camping fee": true
        }
      ]
    },
    "gasPrices": [],
    "url": "https://www.google.com/maps/search/?api=1&query=Yachting%20Point%20campground&query_place_id=ChIJ1yDlDq6pImsRZ3GndUhtIQ0",
    "searchPageUrl": "https://www.google.com/maps/search/tourist%20park%20Snowy%20Mountains%20NSW?hl=en",
    "searchString": "tourist park Snowy Mountains NSW",
    "language": "en",
    "rank": 18,
    "isAdvertisement": false,
    "imageUrl": "https://lh3.googleusercontent.com/gps-cs-s/APNQkAGiqOAU8-F3rEzUgXd-_HCxFgBGm_JVovZDFas7wUgzriqkA_1Rh7VVL6zIApP6NptCcV7aFa9FXkklma549wt9TPmdJUesZL9TiBFDcuwpbNe_O0FXaRFhR9fGMNcfaXfmhf9wO9AVK28=w408-h725-k-no",
    "kgmid": "/g/11rsngrr5m"
  }
]